{
    "tournaments": {
        "na16ar": {
            "title": "NA 2016 Spring Split Regular Season",
            "type": "regular",
            "bo": 3,
            "link": "http://lol.esportswikis.com/wiki/Special:RunQuery/MatchHistoryTournament?MHT%5Btournament%5D=Concept:NA%20LCS%202016%20Spring&MHT%5Btext%5D=Yes&wpRunQuery=true",
            "finished": true
        },
        "na16ap": {
            "title": "NA 2016 Spring Split Playoff",
            "type": "playoff",
            "bo": 5,
            "link": "http://lol.esportswikis.com/wiki/Special:RunQuery/MatchHistoryTournament?MHT%5Btournament%5D=Concept:NA%20LCS%202016%20Spring%20Playoffs&MHT%5Btext%5D=Yes&wpRunQuery=true",
            "finished": true
        },
        "na16br": {
            "title": "NA 2016 Summer Split Regular Season",
            "type": "regular",
            "bo": 3,
            "link": "http://lol.esportswikis.com/wiki/Special:RunQuery/MatchHistoryTournament?MHT%5Btournament%5D=Concept:NA%20LCS%202016%20Summer&MHT%5Btext%5D=Yes&wpRunQuery=true",
            "finished": true
        },
        "na16bp": {
            "title": "NA 2016 Summer Split Playoff",
            "type": "playoff",
            "bo": 5,
            "link": "http://lol.esportswikis.com/wiki/Special:RunQuery/MatchHistoryTournament?MHT%5Btournament%5D=Concept:NA%20LCS%202016%20Summer%20Playoffs&MHT%5Btext%5D=Yes&wpRunQuery=true",
            "finished": true
        },
        "na17ar": {
            "title": "NA 2017 Spring Split Regular Season",
            "type": "regular",
            "bo": 3,
            "link": "http://lol.esportswikis.com/wiki/Special:RunQuery/MatchHistoryTournament?MHT%5Btournament%5D=Concept:NA%20LCS%202017%20Spring&MHT%5Btext%5D=Yes&wpRunQuery=true",
            "finished": false
        },
        "eu16br": {
            "title": "EU 2016 Summer Split Regular Season",
            "type": "regular",
            "bo": 2,
            "link": "http://lol.esportswikis.com/wiki/Special:RunQuery/MatchHistoryTournament?MHT%5Btournament%5D=Concept:EU%20LCS%202016%20Summer&MHT%5Btext%5D=Yes&wpRunQuery=true",
            "finished": true
        },
        "eu16bp": {
            "title": "EU 2016 Summer Split Playoff",
            "type": "playoff",
            "bo": 5,
            "link": "http://lol.esportswikis.com/wiki/Special:RunQuery/MatchHistoryTournament?MHT%5Btournament%5D=Concept:EU%20LCS%202016%20Summer%20Playoffs&MHT%5Btext%5D=Yes&wpRunQuery=true",
            "finished": true
        },
        "eu17ar": {
            "title": "EU 2017 Spring Split Regular Season",
            "type": "regular",
            "bo": 3,
            "link": "http://lol.esportswikis.com/wiki/Special:RunQuery/MatchHistoryTournament?MHT%5Btournament%5D=Concept:EU%20LCS%202017%20Spring&MHT%5Btext%5D=Yes&wpRunQuery=true",
            "finished": false
        },
        "lck15ar": {
            "title": "LCK 2015 Spring Split Regular Season",
            "type": "regular",
            "bo": 3,
            "link": "http://lol.esportswikis.com/wiki/Special:RunQuery/MatchHistoryTournament?MHT%5Btournament%5D=Concept:Champions%202015%20Spring&MHT%5Btext%5D=Yes&wpRunQuery=true",
            "finished": true
        },
        "lck15ap": {
            "title": "LCK 2015 Spring Split Playoff",
            "type": "playoff",
            "bo": 5,
            "link": "http://lol.esportswikis.com/wiki/Special:RunQuery/MatchHistoryTournament?MHT%5Btournament%5D=Concept:Champions%202015%20Spring%20Playoffs&MHT%5Btext%5D=Yes&wpRunQuery=true",
            "finished": true
        },
        "lck15br": {
            "title": "LCK 2015 Summer Split Regular Season",
            "type": "regular",
            "bo": 3,
            "link": "http://lol.esportswikis.com/wiki/Special:RunQuery/MatchHistoryTournament?MHT%5Btournament%5D=Concept:Champions%202015%20Summer&MHT%5Btext%5D=Yes&wpRunQuery=true",
            "finished": true
        },
        "lck15bp": {
            "title": "LCK 2015 Summer Split Playoff",
            "type": "playoff",
            "bo": 5,
            "link": "http://lol.esportswikis.com/wiki/Special:RunQuery/MatchHistoryTournament?MHT%5Btournament%5D=Concept:Champions%202015%20Summer%20Playoffs&MHT%5Btext%5D=Yes&wpRunQuery=true",
            "finished": true
        },
        "lck16ar": {
            "title": "LCK 2016 Spring Split Regular Season",
            "type": "regular",
            "bo": 3,
            "link": "http://lol.esportswikis.com/wiki/Special:RunQuery/MatchHistoryTournament?MHT%5Btournament%5D=Concept:LCK%202016%20Spring&MHT%5Btext%5D=Yes&wpRunQuery=true",
            "finished": true
        },
        "lck16ap": {
            "title": "LCK 2016 Spring Split Playoff",
            "type": "playoff",
            "bo": 5,
            "link": "http://lol.esportswikis.com/wiki/Special:RunQuery/MatchHistoryTournament?MHT%5Btournament%5D=Concept:LCK%202016%20Spring%20Playoffs&MHT%5Btext%5D=Yes&wpRunQuery=true",
            "finished": true
        },
        "lck16br": {
            "title": "LCK 2016 Summer Split Regular Season",
            "type": "regular",
            "bo": 3,
            "link": "http://lol.esportswikis.com/wiki/Special:RunQuery/MatchHistoryTournament?MHT%5Btournament%5D=Concept:LCK%202016%20Summer&MHT%5Btext%5D=Yes&wpRunQuery=true",
            "finished": true
        },
        "lck16bp": {
            "title": "LCK 2016 Summer Split Playoff",
            "type": "playoff",
            "bo": 5,
            "link": "http://lol.esportswikis.com/wiki/Special:RunQuery/MatchHistoryTournament?MHT%5Btournament%5D=Concept:LCK%202016%20Summer%20Playoffs&MHT%5Btext%5D=Yes&wpRunQuery=true",
            "finished": true
        },
        "lck17ar": {
            "title": "LCK 2017 Spring Split Regular Season",
            "type": "regular",
            "bo": 3,
            "link": "http://lol.esportswikis.com/wiki/Special:RunQuery/MatchHistoryTournament?MHT%5Btournament%5D=Concept:LCK%202017%20Spring&MHT%5Btext%5D=Yes&wpRunQuery=true",
            "finished": false
        },
        "lpl16ar": {
            "title": "LPL 2016 Spring Split Regular Season",
            "type": "regular",
            "bo": 3,
            "link": "http://lol.esportswikis.com/wiki/Special:RunQuery/MatchHistoryTournament?MHT%5Btournament%5D=Concept:LPL%202016%20Spring&MHT%5Btext%5D=Yes&wpRunQuery=true",
            "finished": true
        },
        "lpl16ap": {
            "title": "LPL 2016 Spring Split Playoff",
            "type": "playoff",
            "bo": 5,
            "link": "http://lol.esportswikis.com/wiki/Special:RunQuery/MatchHistoryTournament?MHT%5Btournament%5D=Concept:LPL%202016%20Spring%20Playoffs&MHT%5Btext%5D=Yes&wpRunQuery=true",
            "finished": true
        },
        "lpl16br": {
            "title": "LPL 2016 Summer Split Regular Season",
            "type": "regular",
            "bo": 3,
            "link": "http://lol.esportswikis.com/wiki/Special:RunQuery/MatchHistoryTournament?MHT%5Btournament%5D=Concept:LPL%202016%20Summer&MHT%5Btext%5D=Yes&wpRunQuery=true",
            "finished": true
        },
        "lpl16bp": {
            "title": "LPL 2016 Summer Split Playoff",
            "type": "playoff",
            "bo": 5,
            "link": "http://lol.esportswikis.com/wiki/Special:RunQuery/MatchHistoryTournament?MHT%5Btournament%5D=Concept:LPL%202016%20Summer%20Playoffs&MHT%5Btext%5D=Yes&wpRunQuery=true",
            "finished": true
        },
        "lpl17ar": {
            "title": "LPL 2017 Spring Split Regular Season",
            "type": "regular",
            "bo": 3,
            "link": "http://lol.esportswikis.com/wiki/Special:RunQuery/MatchHistoryTournament?MHT%5Btournament%5D=Concept:LPL%202017%20Spring&MHT%5Btext%5D=Yes&wpRunQuery=true",
            "finished": false
        },
        "lms16br": {
            "title": "LMS 2016 Summer Split Regular Season",
            "type": "regular",
            "bo": 2,
            "link": "http://lol.esportswikis.com/wiki/Special:RunQuery/MatchHistoryTournament?MHT%5Btournament%5D=Concept:LMS%202016%20Summer&MHT%5Btext%5D=Yes&wpRunQuery=true",
            "finished": true
        },
        "lms16bp": {
            "title": "LMS 2016 Summer Split Playoff",
            "type": "playoff",
            "bo": 5,
            "link": "http://lol.esportswikis.com/wiki/Special:RunQuery/MatchHistoryTournament?MHT%5Btournament%5D=Concept:LMS%202016%20Summer%20Playoffs&MHT%5Btext%5D=Yes&wpRunQuery=true",
            "finished": true
        },
        "lms17ar": {
            "title": "LMS 2017 Spring Split Regular Season",
            "type": "regular",
            "bo": 3,
            "link": "http://lol.esportswikis.com/wiki/Special:RunQuery/MatchHistoryTournament?MHT%5Btournament%5D=Concept:LMS%202017%20Spring&MHT%5Btext%5D=Yes&wpRunQuery=true",
            "finished": false
        },
        "lspl17ar": {
            "title": "LSPL 2017 Spring Split Regular Season",
            "type": "regular",
            "bo": 3,
            "link": "http://lol.esportswikis.com/wiki/Special:RunQuery/MatchHistoryTournament?MHT%5Btournament%5D=Concept:LSPL%202017%20Spring&MHT%5Btext%5D=Yes&wpRunQuery=true",
            "finished": false
        }
    },
    "combined": {
        "new": ["na17ar", "eu17ar", "lck17ar", "lpl17ar", "lms17ar"],
        "na16a": ["na16ar", "na16ap"],
        "na16b": ["na16br", "na16bp"],
        "na": ["na17ar"],
        "eu16b": ["eu16br", "eu16bp"],
        "eu": ["eu17ar"],
        "lcks": ["lck15ar", "lck15ap", "lck15br", "lck15bp", "lck16ar", "lck16ap", "lck16br", "lck16bp"],
        "bor": ["lck15ar", "lck15br", "lck16ar", "lck16br", "lpl16ar", "lpl16br", "eu16br", "na16br", "lms16br"],
        "2016r": ["lck16ar", "lck16br", "lpl16br", "eu16br", "na16br", "lms16br"],
        "2016br": ["lck16br", "lpl16br", "eu16br", "na16br", "lms16br"],
        "2016brbo3": ["lck16br", "lpl16br", "na16br"],
        "2017ar": ["lck17ar", "lpl17ar", "eu17ar", "na17ar"],
        "2017ar2": ["lck17ar", "lpl17ar", "eu17ar", "na17ar", "lms17ar"],
        "lck15a": ["lck15ar", "lck15ap"],
        "lck15b": ["lck15br", "lck15bp"],
        "lck16a": ["lck16ar", "lck16ap"],
        "lck16b": ["lck16br", "lck16bp"],
        "lck": ["lck17ar"],
        "lpl16a": ["lpl16ar", "lpl16ap"],
        "lpl16b": ["lpl16br", "lpl16bp"],
        "lpl": ["lpl17ar"],
        "lms16b": ["lms16br", "lms16bp"],
        "lms": ["lms17ar"]
    }
}